<!-- Last project change: 2021-02-01 23:28:33 (2021-02-02 04:28:33) -->
<PrjQlikViewProject>
  <GLOBAL>
    <AllPropertiesFileName>AllProperties.xml</AllPropertiesFileName>
    <DocBinaryFileName>DocBinary.dat</DocBinaryFileName>
    <DocInternalsFileName>DocInternals.xml</DocInternalsFileName>
    <DocPropertiesFileName>DocProperties.xml</DocPropertiesFileName>
    <LoadScriptFileName>LoadScript.txt</LoadScriptFileName>
    <ModuleFileName>Module.txt</ModuleFileName>
    <TopLayoutFileName>TopLayout.xml</TopLayoutFileName>
  </GLOBAL>
  <SHEETS>
    <PrjSheetProperties>
      <SheetId>Document\SH01</SheetId>
      <IsActive>true</IsActive>
      <ChildObjects>
        <PrjFrameParentDef>
          <ObjectId>Document\TX02</ObjectId>
          <Rect>
            <Left>2403</Left>
            <Top>569</Top>
            <Width>450</Width>
            <Height>450</Height>
          </Rect>
          <MinimizedRect>
            <Left>0</Left>
            <Top>0</Top>
            <Width>297</Width>
            <Height>102</Height>
          </MinimizedRect>
          <ShowMode>1</ShowMode>
          <ZedLevel>-1</ZedLevel>
        </PrjFrameParentDef>
        <PrjFrameParentDef>
          <ObjectId>Document\TX01</ObjectId>
          <Rect>
            <Left>1566</Left>
            <Top>500</Top>
            <Width>450</Width>
            <Height>450</Height>
          </Rect>
          <MinimizedRect>
            <Left>0</Left>
            <Top>0</Top>
            <Width>297</Width>
            <Height>102</Height>
          </MinimizedRect>
          <ShowMode>1</ShowMode>
          <ZedLevel>-1</ZedLevel>
        </PrjFrameParentDef>
      </ChildObjects>
    </PrjSheetProperties>
  </SHEETS>
  <REPORTS></REPORTS>
  <ContainerMembers></ContainerMembers>
</PrjQlikViewProject>
